msprt/__init__.py
msprt/msprt_.py
msprt-0.1.2.dist-info/LICENSE
msprt-0.1.2.dist-info/WHEEL
msprt-0.1.2.dist-info/METADATA
msprt-0.1.2.dist-info/RECORD
