Metadata-Version: 2.1
Name: msprt
Version: 0.1.2
Summary: 
License: GPL-3.0-or-later
Author: Ovidijus Kuzminas
Author-email: ovidijus4733@gmail.com
Requires-Python: >=3.10,<3.13
Classifier: License :: OSI Approved :: GNU General Public License v3 or later (GPLv3+)
Classifier: Programming Language :: Python :: 3
Classifier: Programming Language :: Python :: 3.10
Classifier: Programming Language :: Python :: 3.11
Requires-Dist: matplotlib (>=3.8.1,<4.0.0)
Requires-Dist: numpy (>=1.26.1,<2.0.0)
Requires-Dist: scipy (>=1.11.3,<2.0.0)
